check_yamlschema.py
check_yamlschema-0.0.7.dist-info/licenses/LICENSE
check_yamlschema-0.0.7.dist-info/METADATA
check_yamlschema-0.0.7.dist-info/WHEEL
check_yamlschema-0.0.7.dist-info/entry_points.txt
check_yamlschema-0.0.7.dist-info/top_level.txt
check_yamlschema-0.0.7.dist-info/RECORD
