Metadata-Version: 2.4
Name: check-yamlschema
Version: 0.0.7
Summary: A CLI and pre-commit hooks for jsonschema validation in YAML files with multiple documents
Home-page: https://github.com/jmlrt/check-yamlschema
Author: Julien Mailleret
Author-email: julien@mailleret.fr
License: MIT
Requires-Python: >=3.9
License-File: LICENSE
Requires-Dist: jsonschema
Requires-Dist: pyyaml
Requires-Dist: requests
Dynamic: license-file
